oofem/__init__.py
oofem/oofempy.so
oofem/util.py
oofem-2.6.0.dev1.dist-info/COPYING.LGPLv2.1
oofem-2.6.0.dev1.dist-info/METADATA
oofem-2.6.0.dev1.dist-info/WHEEL
oofem-2.6.0.dev1.dist-info/entry_points.txt
oofem-2.6.0.dev1.dist-info/RECORD
