Metadata-Version: 2.1
Name: oofem
Version: 2.6.0.dev1
Summary: oofem etc
License:                   GNU LESSER GENERAL PUBLIC LICENSE
